cms/cache_logic.v
// ======================================================================
// BASIC LOGIC BLOCK FOR UI LOGIC DIAGRAM
// Simple combinational circuit: TAGMATCH -> VALID -> AND -> MUX -> OUTPUT
// ======================================================================
module cache_logic_basic(
    input  wire        valid,
    input  wire [31:0] address_tag,
    input  wire [31:0] stored_tag,
    
    output wire        tag_match,
    output wire        and_output,
    output wire        hit_output
);

    // TAG MATCH BLOCK
    assign tag_match = (address_tag == stored_tag);

    // AND GATE
    assign and_output = valid & tag_match;

    // MUX (Hit/Miss)
    assign hit_output = and_output ? 1'b1 : 1'b0;

endmodule


// ======================================================================
// COMPLETE CACHE HIT DETECTOR (used inside L1 and L2 controllers)
// ======================================================================
module cache_hit_detector (
    input wire clk,
    input wire rst_n,
    
    input wire [31:0] address,
    input wire [15:0] num_sets,
    input wire [7:0]  offset_bits,
    input wire [7:0]  index_bits,

    input wire [31:0] stored_tag,
    input wire        valid_bit,

    output reg  [15:0] set_index,
    output reg  [31:0] tag,
    output reg  [31:0] block_offset,
    output wire        tag_match,
    output wire        hit_signal
);

    // Address decode (Combinational)
    always @(*) begin
        // Calculate masks based on bit widths
        block_offset = address & ((1 << offset_bits) - 1);
        set_index    = (address >> offset_bits) & ((1 << index_bits) - 1);
        tag          = address >> (offset_bits + index_bits);
    end

    // Compare Tag
    assign tag_match = (tag == stored_tag);

    // HIT Calculation: Must be Valid AND Tag Match
    assign hit_signal = valid_bit & tag_match;

endmodule


// ======================================================================
// L1 CACHE CONTROLLER
// ======================================================================
module l1_cache_controller(
    input  wire        clk,
    input  wire        rst_n,
    input  wire [31:0] address,
    input  wire        read_write, // 0 = Read, 1 = Write
    input  wire [7:0]  data_in,

    input  wire        valid,
    input  wire [31:0] stored_tag,
    input  wire [31:0] stored_data,

    output reg         l1_hit,
    output reg         l1_miss,
    output reg  [7:0]  data_out,

    output wire [31:0] decoded_tag,
    output wire [15:0] decoded_index,
    output wire [31:0] decoded_offset
);

    wire l1_hit_internal;

    // Instantiate Detector for L1 (Example: 256 sets, 64-byte blocks)
    cache_hit_detector hit_det(
        .clk(clk), .rst_n(rst_n),
        .address(address),
        .num_sets(16'd256),
        .offset_bits(8'd6),   // 6 bits for 64-byte block
        .index_bits(8'd8),    // 8 bits for 256 sets
        .stored_tag(stored_tag),
        .valid_bit(valid),
        .set_index(decoded_index),
        .tag(decoded_tag),
        .block_offset(decoded_offset),
        .tag_match(),
        .hit_signal(l1_hit_internal)
    );

    // Registered Output Logic
    always @(posedge clk or negedge rst_n) begin
        if (!rst_n) begin
            l1_hit  <= 0;
            l1_miss <= 0;
            data_out <= 8'h00;
        end else begin
            l1_hit  <= l1_hit_internal;
            l1_miss <= ~l1_hit_internal;

            // Only output data on HIT and READ operation
            if (l1_hit_internal && !read_write)
                data_out <= stored_data;
            else
                data_out <= 8'h00; // Default/Safe value
        end
    end
endmodule


// ======================================================================
// L2 CACHE CONTROLLER
// ======================================================================
module l2_cache_controller(
    input  wire        clk,
    input  wire        rst_n,
    input  wire [31:0] address,
    input  wire        read_write,
    input  wire [7:0]  data_in,

    input  wire        valid,
    input  wire [31:0] stored_tag,
    input  wire [31:0] stored_data,

    output reg         l2_hit,
    output reg         l2_miss,
    output reg  [7:0]  data_out
);

    wire l2_hit_internal;

    // Instantiate Detector for L2 (Example: 4096 sets, 64-byte blocks)
    cache_hit_detector hit_det(
        .clk(clk), .rst_n(rst_n),
        .address(address),
        .num_sets(16'd4096),
        .offset_bits(8'd6),
        .index_bits(8'd12),   // 12 bits for 4096 sets
        .stored_tag(stored_tag),
        .valid_bit(valid),
        .set_index(),
        .tag(),
        .block_offset(),
        .tag_match(),
        .hit_signal(l2_hit_internal)
    );

    always @(posedge clk or negedge rst_n) begin
        if (!rst_n) begin
            l2_hit  <= 0;
            l2_miss <= 0;
            data_out <= 8'h00;
        end else begin
            l2_hit  <= l2_hit_internal;
            l2_miss <= ~l2_hit_internal;

            if (l2_hit_internal && !read_write)
                data_out <= stored_data;
            else
                data_out <= 8'h00;
        end
    end
endmodule


// ======================================================================
// CACHE HIERARCHY
// ======================================================================
module cache_hierarchy(
    input  wire        clk,
    input  wire        rst_n,
    input  wire [31:0] address,
    input  wire        read_write,
    input  wire [7:0]  data_in,

    // Inputs simulating data retrieved from internal L1 memory array
    input  wire        l1_valid,
    input  wire [31:0] l1_stored_tag,
    input  wire [7:0]  l1_data,

    // Inputs simulating data retrieved from internal L2 memory array
    input  wire        l2_valid,
    input  wire [31:0] l2_stored_tag,
    input  wire [7:0]  l2_data,

    output wire        l1_hit,
    output wire        l1_miss,
    output wire        l2_hit,
    output wire        l2_miss,
    output wire [7:0]  data_out,
    output wire        memory_access
);

    // Internal data wires driven by controllers
    wire [7:0] l1_dout_internal;
    wire [7:0] l2_dout_internal;

    // L1 Controller Instance
    l1_cache_controller l1_ctrl(
        .clk(clk), .rst_n(rst_n),
        .address(address),
        .read_write(read_write),
        .data_in(data_in),
        .valid(l1_valid),
        .stored_tag(l1_stored_tag),
        .stored_data(l1_data),
        .l1_hit(l1_hit),
        .l1_miss(l1_miss),
        .data_out(l1_dout_internal), // Capture internal data output
        .decoded_tag(),
        .decoded_index(),
        .decoded_offset()
    );

    // L2 Controller Instance
    l2_cache_controller l2_ctrl(
        .clk(clk), .rst_n(rst_n),
        .address(address),
        .read_write(read_write),
        .data_in(data_in),
        .valid(l2_valid),
        .stored_tag(l2_stored_tag),
        .stored_data(l2_data),
        .l2_hit(l2_hit),
        .l2_miss(l2_miss),
        .data_out(l2_dout_internal)  // Capture internal data output
    );

    // ------------------------------------------------------------------
    // HIERARCHY LOGIC
    // ------------------------------------------------------------------
    
    // Main Memory is accessed only if BOTH L1 and L2 miss
    assign memory_access = l1_miss & l2_miss;

    // Muxing Data Output:
    // If L1 Hit -> Output L1 Data
    // Else If L2 Hit -> Output L2 Data
    // Else -> 0 (or High-Z)
    assign data_out = l1_hit ? l1_dout_internal : 
                      l2_hit ? l2_dout_internal : 8'h00;

endmodule

cms/cache_sim_tb.v
// Testbench that generates waveforms for cache hierarchy
`timescale 1ns/1ps

module cache_hierarchy_tb;

    // Clock + reset
    reg clk;
    reg rst_n;

    // Inputs
    reg [31:0] address;
    reg read_write;
    reg [7:0] data_in;

    // L1 inputs (Simulated tag/data from cache memory array)
    reg l1_valid;
    reg [31:0] l1_tag;
    reg [7:0] l1_data;

    // L2 inputs (Simulated tag/data from cache memory array)
    reg l2_valid;
    reg [31:0] l2_tag;
    reg [7:0] l2_data;

    // Outputs
    wire l1_hit, l1_miss;
    wire l2_hit, l2_miss;
    wire [7:0] data_out;
    wire memory_access;

    // --------------------------------------------------------------------
    // DUT INSTANTIATION
    // --------------------------------------------------------------------
    cache_hierarchy dut (
        .clk(clk),
        .rst_n(rst_n),
        .address(address),
        .read_write(read_write),
        .data_in(data_in),
        .l1_valid(l1_valid),
        .l1_stored_tag(l1_tag),
        .l1_data(l1_data),
        .l2_valid(l2_valid),
        .l2_stored_tag(l2_tag),
        .l2_data(l2_data),
        .l1_hit(l1_hit),
        .l1_miss(l1_miss),
        .l2_hit(l2_hit),
        .l2_miss(l2_miss),
        .data_out(data_out),
        .memory_access(memory_access)
    );

    // Clock Generation (100 MHz -> 10ns period)
    initial begin
        clk = 0;
        forever #5 clk = ~clk;
    end

    // Test Sequence
    initial begin
        // VCD dump for waveform viewing
        $dumpfile("cache_waveform.vcd");
        $dumpvars(0, cache_hierarchy_tb);

        // Initialize signals
        rst_n = 0;
        address = 0;
        read_write = 0;
        data_in = 0;
        l1_valid = 0;
        l1_tag = 0;
        l1_data = 0;
        l2_valid = 0;
        l2_tag = 0;
        l2_data = 0;

        // Release Reset
        #20 rst_n = 1;

        // --------------------------------------------------------
        // TEST 1: L1 HIT (READ)
        // --------------------------------------------------------
        #10;
        address = 32'h00000010;
        read_write = 0;         // READ
        l1_valid = 1;
        l1_tag = 32'h00000000;  // Matches tag for 0x10
        l1_data = 8'hAA;
        l2_valid = 0;           // L2 irrelevant
        
        $display("--------------------------------------------------");
        $display("T=%0t: TEST 1 -> Initiating Read 0x10 (Expect L1 HIT)", $time);

        // --------------------------------------------------------
        // TEST 2: L1 MISS, L2 HIT
        // --------------------------------------------------------
        #10;
        address = 32'h00000020;
        read_write = 0;
        l1_valid = 0;          // L1 MISS
        l1_tag = 32'h00000001; // Mismatch
        l1_data = 8'h00;

        l2_valid = 1;          // L2 HIT
        l2_tag = 32'h00000000; // Matches tag for 0x20
        l2_data = 8'hBB;

        $display("--------------------------------------------------");
        $display("T=%0t: TEST 2 -> Initiating Read 0x20 (Expect L1 MISS, L2 HIT)", $time);

        // --------------------------------------------------------
        // TEST 3: L1 MISS, L2 MISS -> MEMORY ACCESS
        // --------------------------------------------------------
        #10;
        address = 32'h00000040;
        read_write = 0;

        l1_valid = 0;
        l2_valid = 0;
        l1_tag = 32'h1;
        l2_tag = 32'h1;
        l1_data = 8'h00;
        l2_data = 8'h00;

        $display("--------------------------------------------------");
        $display("T=%0t: TEST 3 -> Initiating Read 0x40 (Expect BOTH MISS)", $time);

        // --------------------------------------------------------
        // TEST 4: WRITE with L1 HIT
        // --------------------------------------------------------
        #10;
        address = 32'h00000050;
        read_write = 1;      // WRITE
        data_in = 8'hCC;
        
        l1_valid = 1;
        l1_tag  = 32'h00000000;
        l1_data = 8'hDD; // Old data
        l2_valid = 0;

        $display("--------------------------------------------------");
        $display("T=%0t: TEST 4 -> Initiating Write 0x50 (Expect L1 HIT)", $time);

        // --------------------------------------------------------
        // TEST 5: L1 VALID but TAG MISMATCH
        // --------------------------------------------------------
        #10;
        address = 32'h00000060;
        read_write = 0;

        l1_valid = 1;
        l1_tag = 32'hFFFF_FFFF; // Wrong tag -> MISS

        l2_valid = 1;
        l2_tag = 32'h00000000;
        l2_data = 8'hFF;

        $display("--------------------------------------------------");
        $display("T=%0t: TEST 5 -> Initiating Read 0x60 (Expect Tag Mismatch)", $time);

        #20;
        $display("--------------------------------------------------");
        $display("Simulation Finished.");
        $finish;
    end

    // Monitor hits/misses on positive clock edge
    always @(posedge clk) begin
        // We check signals slightly after edge to ensure stability in simulation
        #1; 
        if (rst_n) begin
            if (l1_hit)
                $display("  [RESULT] Time=%0t: L1 HIT for Address=0x%h Data=0x%h", $time, address, data_out);

            else if (l1_miss && l2_hit)
                $display("  [RESULT] Time=%0t: L1 MISS, L2 HIT for Address=0x%h Data=0x%h", $time, address, data_out);

            else if (l1_miss && l2_miss)
                $display("  [RESULT] Time=%0t: L1 MISS, L2 MISS -> Accessing Main Memory (Addr=0x%h)", $time, address);
        end
    end

endmodule

cms/cache_waveform.vcd
$date
	Sat Dec 06 23:18:32 2025
$end
$version
	Icarus Verilog
$end
$timescale
	1ps
$end
$scope module cache_hierarchy_tb $end
$var wire 1 ! memory_access $end
$var wire 1 " l2_miss $end
$var wire 1 # l2_hit $end
$var wire 1 $ l1_miss $end
$var wire 1 % l1_hit $end
$var wire 8 & data_out [7:0] $end
$var reg 32 ' address [31:0] $end
$var reg 1 ( clk $end
$var reg 8 ) data_in [7:0] $end
$var reg 8 * l1_data [7:0] $end
$var reg 32 + l1_tag [31:0] $end
$var reg 1 , l1_valid $end
$var reg 8 - l2_data [7:0] $end
$var reg 32 . l2_tag [31:0] $end
$var reg 1 / l2_valid $end
$var reg 1 0 read_write $end
$var reg 1 1 rst_n $end
$scope module dut $end
$var wire 32 2 address [31:0] $end
$var wire 1 ( clk $end
$var wire 8 3 data_in [7:0] $end
$var wire 8 4 l1_data [7:0] $end
$var wire 32 5 l1_stored_tag [31:0] $end
$var wire 1 , l1_valid $end
$var wire 8 6 l2_data [7:0] $end
$var wire 32 7 l2_stored_tag [31:0] $end
$var wire 1 / l2_valid $end
$var wire 1 ! memory_access $end
$var wire 1 0 read_write $end
$var wire 1 1 rst_n $end
$var wire 1 " l2_miss $end
$var wire 1 # l2_hit $end
$var wire 8 8 l2_dout_internal [7:0] $end
$var wire 1 $ l1_miss $end
$var wire 1 % l1_hit $end
$var wire 8 9 l1_dout_internal [7:0] $end
$var wire 8 : data_out [7:0] $end
$scope module l1_ctrl $end
$var wire 32 ; address [31:0] $end
$var wire 1 ( clk $end
$var wire 8 < data_in [7:0] $end
$var wire 1 0 read_write $end
$var wire 1 1 rst_n $end
$var wire 32 = stored_data [31:0] $end
$var wire 32 > stored_tag [31:0] $end
$var wire 1 , valid $end
$var wire 1 ? l1_hit_internal $end
$var wire 32 @ decoded_tag [31:0] $end
$var wire 32 A decoded_offset [31:0] $end
$var wire 16 B decoded_index [15:0] $end
$var reg 8 C data_out [7:0] $end
$var reg 1 % l1_hit $end
$var reg 1 $ l1_miss $end
$scope module hit_det $end
$var wire 32 D address [31:0] $end
$var wire 1 ( clk $end
$var wire 1 ? hit_signal $end
$var wire 8 E index_bits [7:0] $end
$var wire 16 F num_sets [15:0] $end
$var wire 8 G offset_bits [7:0] $end
$var wire 1 1 rst_n $end
$var wire 32 H stored_tag [31:0] $end
$var wire 1 , valid_bit $end
$var wire 1 I tag_match $end
$var reg 32 J block_offset [31:0] $end
$var reg 16 K set_index [15:0] $end
$var reg 32 L tag [31:0] $end
$upscope $end
$upscope $end
$scope module l2_ctrl $end
$var wire 32 M address [31:0] $end
$var wire 1 ( clk $end
$var wire 8 N data_in [7:0] $end
$var wire 1 0 read_write $end
$var wire 1 1 rst_n $end
$var wire 32 O stored_data [31:0] $end
$var wire 32 P stored_tag [31:0] $end
$var wire 1 / valid $end
$var wire 1 Q l2_hit_internal $end
$var reg 8 R data_out [7:0] $end
$var reg 1 # l2_hit $end
$var reg 1 " l2_miss $end
$scope module hit_det $end
$var wire 32 S address [31:0] $end
$var wire 1 ( clk $end
$var wire 1 Q hit_signal $end
$var wire 8 T index_bits [7:0] $end
$var wire 16 U num_sets [15:0] $end
$var wire 8 V offset_bits [7:0] $end
$var wire 1 1 rst_n $end
$var wire 32 W stored_tag [31:0] $end
$var wire 1 / valid_bit $end
$var wire 1 X tag_match $end
$var reg 32 Y block_offset [31:0] $end
$var reg 16 Z set_index [15:0] $end
$var reg 32 [ tag [31:0] $end
$upscope $end
$upscope $end
$upscope $end
$upscope $end
$enddefinitions $end
$comment Show the parameter values. $end
$dumpall
$end
#0
$dumpvars
b0 [
b0 Z
b0 Y
1X
b0 W
b110 V
b1000000000000 U
b1100 T
b0 S
b0 R
0Q
b0 P
b0 O
b0 N
b0 M
b0 L
b0 K
b0 J
1I
b0 H
b110 G
b100000000 F
b1000 E
b0 D
b0 C
b0 B
b0 A
b0 @
0?
b0 >
b0 =
b0 <
b0 ;
b0 :
b0 9
b0 8
b0 7
b0 6
b0 5
b0 4
b0 3
b0 2
01
00
0/
b0 .
b0 -
0,
b0 +
b0 *
b0 )
0(
b0 '
b0 &
0%
0$
0#
0"
0!
$end
#5000
1(
#10000
0(
#15000
1(
#20000
0(
11
#25000
1!
1"
1$
1(
#30000
1?
b10000 A
b10000 J
b10000 Y
0(
b10101010 =
b10101010 *
b10101010 4
1,
b10000 '
b10000 2
b10000 ;
b10000 D
b10000 M
b10000 S
#35000
0!
b10101010 &
b10101010 :
b10101010 9
b10101010 C
0$
1%
1(
#40000
1Q
0?
b100000 A
b100000 J
b100000 Y
0(
b10111011 O
b10111011 -
b10111011 6
1/
b0 =
b0 *
b0 4
0I
b1 +
b1 5
b1 >
b1 H
0,
b100000 '
b100000 2
b100000 ;
b100000 D
b100000 M
b100000 S
#45000
b10111011 &
b10111011 :
b10111011 8
b10111011 R
0"
1#
b0 9
b0 C
1$
0%
1(
#50000
0Q
b1 B
b1 K
b0 A
b0 J
b1 Z
b0 Y
0(
b0 O
b0 -
b0 6
0X
b1 .
b1 7
b1 P
b1 W
0/
b1000000 '
b1000000 2
b1000000 ;
b1000000 D
b1000000 M
b1000000 S
#55000
b0 &
b0 :
1!
b0 8
b0 R
1"
0#
1(
#60000
1?
b10000 A
b10000 J
b10000 Y
0(
b11011101 =
b11011101 *
b11011101 4
1I
b0 +
b0 5
b0 >
b0 H
1,
b11001100 )
b11001100 3
b11001100 <
b11001100 N
10
b1010000 '
b1010000 2
b1010000 ;
b1010000 D
b1010000 M
b1010000 S
#65000
0!
0$
1%
1(
#70000
1Q
0?
b100000 A
b100000 J
b100000 Y
0(
b11111111 O
b11111111 -
b11111111 6
1X
b0 .
b0 7
b0 P
b0 W
1/
0I
b11111111111111111111111111111111 +
b11111111111111111111111111111111 5
b11111111111111111111111111111111 >
b11111111111111111111111111111111 H
00
b1100000 '
b1100000 2
b1100000 ;
b1100000 D
b1100000 M
b1100000 S
#75000
b11111111 &
b11111111 :
1$
0%
b11111111 8
b11111111 R
0"
1#
1(
